mindtrace/core/__init__.py
mindtrace/core/base/__init__.py
mindtrace/core/base/mindtrace_base.py
mindtrace/core/config/__init__.py
mindtrace/core/config/config.ini
mindtrace/core/config/config.py
mindtrace/core/logging/__init__.py
mindtrace/core/logging/logger.py
mindtrace/core/observables/context_listener.py
mindtrace/core/observables/event_bus.py
mindtrace/core/observables/observable_context.py
mindtrace/core/samples/echo_task.py
mindtrace/core/types/__init__.py
mindtrace/core/types/bounding_box.py
mindtrace/core/types/rotated_rect.py
mindtrace/core/types/task_schema.py
mindtrace/core/utils/__init__.py
mindtrace/core/utils/checks.py
mindtrace/core/utils/conversions.py
mindtrace/core/utils/download.py
mindtrace/core/utils/dynamic.py
mindtrace/core/utils/hashing.py
mindtrace/core/utils/ini.py
mindtrace/core/utils/lambdas.py
mindtrace/core/utils/paths.py
mindtrace/core/utils/system_metrics_collector.py
mindtrace/core/utils/timers.py
mindtrace_core-0.8.0.dist-info/licenses/LICENSE
mindtrace_core-0.8.0.dist-info/METADATA
mindtrace_core-0.8.0.dist-info/WHEEL
mindtrace_core-0.8.0.dist-info/top_level.txt
mindtrace_core-0.8.0.dist-info/RECORD
