Metadata-Version: 2.4
Name: mindtrace-core
Version: 0.8.0
Summary: Core functionality for Mindtrace
Author: Mindtrace Team
License-Expression: Apache-2.0
Project-URL: Homepage, https://mindtrace.ai
Project-URL: Repository, https://github.com/mindtrace/mindtrace/blob/main/mindtrace/core
Classifier: Programming Language :: Python :: 3
Classifier: Programming Language :: Python :: 3.12
License-File: LICENSE
Requires-Dist: pillow>=11.2.1
Requires-Dist: psutil>=5.9.0
Requires-Dist: pydantic>=2.11.1
Requires-Dist: pydantic-settings>=2.10.1
Requires-Dist: structlog>=24.4.0
Requires-Dist: tqdm>=4.67.1
Requires-Dist: urllib3>=2.2.0
Dynamic: license-file
